netnir/__init__.py
netnir/cli.py
netnir/constants.py
netnir/core/__init__.py
netnir/core/credentials.py
netnir/core/inventory.py
netnir/core/output.py
netnir/core/connection/__init__.py
netnir/core/connection/netconf.py
netnir/core/connection/netmiko.py
netnir/core/tasks/__init__.py
netnir/core/tasks/config_plan.py
netnir/core/tasks/inventory.py
netnir/core/tasks/netconf.py
netnir/core/tasks/ssh.py
netnir/core/tasks/user.py
netnir/core/tasks/fetch/__init__.py
netnir/core/tasks/fetch/config.py
netnir/helpers/__init__.py
netnir/helpers/colors.py
netnir/helpers/defaults.py
netnir/helpers/common/__init__.py
netnir/helpers/common/args.py
netnir/helpers/scaffold/__init__.py
netnir/helpers/scaffold/command.py
netnir/helpers/scaffold/subcommand.py
netnir/plugins/__init__.py
netnir/plugins/facts.py
netnir/plugins/hier.py
netnir/plugins/netconf.py
netnir/plugins/netmiko.py
netnir/plugins/template.py
netnir-0.0.20.data/scripts/netnir
netnir-0.0.20.dist-info/LICENSE
netnir-0.0.20.dist-info/METADATA
netnir-0.0.20.dist-info/WHEEL
netnir-0.0.20.dist-info/top_level.txt
netnir-0.0.20.dist-info/RECORD
